epx/__init__.py
epx/attribute/__init__.py
epx/attribute/attribute.py
epx/core/__init__.py
epx/core/cloud/__init__.py
epx/core/cloud/auth.py
epx/core/cloud/config.py
epx/core/errors/__init__.py
epx/core/errors/api_errors.py
epx/core/errors/validation_error.py
epx/core/models/__init__.py
epx/core/models/synthpop.py
epx/core/types/__init__.py
epx/core/types/common.py
epx/core/types/error_type.py
epx/core/utils/__init__.py
epx/core/utils/config.py
epx/core/utils/file.py
epx/core/utils/http_request.py
epx/core/utils/random.py
epx/core/utils/s3_helpers.py
epx/job/__init__.py
epx/job/fred_job.py
epx/job/job.py
epx/job/config/fred_model_config.py
epx/job/config/fred_model_config_sweep.py
epx/job/result/__init__.py
epx/job/result/fred_job_results.py
epx/job/status/__init__.py
epx/job/status/fred_job_status.py
epx/run/__init__.py
epx/run/fred_run.py
epx/run/fs.py
epx/run/run.py
epx/run/exec/__init__.py
epx/run/exec/compat.py
epx/run/exec/cloud/__init__.py
epx/run/exec/cloud/strategy.py
epx/run/result/__init__.py
epx/run/result/fred_run_results.py
epx/run/status/__init__.py
epx/run/status/fred_run_status.py
epx-1.2.2.dist-info/METADATA
epx-1.2.2.dist-info/WHEEL
epx-1.2.2.dist-info/licenses/LICENSE
epx-1.2.2.dist-info/RECORD
