Metadata-Version: 2.4
Name: epx
Version: 1.2.2
Summary: Client for running simulations with Epistemix Platform Cloud.
Author-email: Andrew Lane <andrew.lane@epistemix.com>
License: Copyright 2024 Epistemix, Inc.
License-File: LICENSE
Keywords: ABM,Epistemix,FRED,client
Classifier: Development Status :: 4 - Beta
Classifier: Intended Audience :: Developers
Classifier: Intended Audience :: Education
Classifier: Intended Audience :: Science/Research
Classifier: License :: OSI Approved :: MIT License
Classifier: Programming Language :: Python :: 3
Classifier: Programming Language :: Python :: 3.10
Classifier: Programming Language :: Python :: 3.11
Classifier: Programming Language :: Python :: 3.12
Classifier: Programming Language :: Python :: 3.13
Requires-Python: >=3.10
Requires-Dist: networkx
Requires-Dist: numpy<2.0
Requires-Dist: pandas>=2.1
Requires-Dist: pyarrow
Requires-Dist: pydantic>=2
Requires-Dist: pydot
Requires-Dist: requests
Requires-Dist: types-networkx
Provides-Extra: dev
Requires-Dist: black; extra == 'dev'
Requires-Dist: flake8; extra == 'dev'
Requires-Dist: flake8-black; extra == 'dev'
Requires-Dist: flake8-pyproject; extra == 'dev'
Requires-Dist: multimethod<=1.10; extra == 'dev'
Requires-Dist: mypy; extra == 'dev'
Requires-Dist: pandas-stubs; extra == 'dev'
Requires-Dist: pandera; extra == 'dev'
Requires-Dist: pytest; extra == 'dev'
Requires-Dist: pytest-cov; extra == 'dev'
Requires-Dist: sphinx; extra == 'dev'
Requires-Dist: types-requests; extra == 'dev'
